ptrack/__init__.py
ptrack/main.py
ptrack/media.py
ptrack/methods.py
ptrack/urlDeconstruct.py
ptrack-2.0.3.dist-info/LICENSE
ptrack-2.0.3.dist-info/METADATA
ptrack-2.0.3.dist-info/WHEEL
ptrack-2.0.3.dist-info/entry_points.txt
ptrack-2.0.3.dist-info/top_level.txt
ptrack-2.0.3.dist-info/RECORD
